file_storage/__init__.py
file_storage/composite.py
file_storage/creator.py
file_storage/disk.py
file_storage/entities.py
file_storage/ftp.py
file_storage/s3.py
file_storage/storage.py
file_storage-0.2.5.dist-info/LICENSE
file_storage-0.2.5.dist-info/WHEEL
file_storage-0.2.5.dist-info/METADATA
file_storage-0.2.5.dist-info/RECORD
