Metadata-Version: 2.1
Name: file-storage
Version: 0.2.5
Summary: Universal tool for file storages
License: GPL-3.0 License
Author: Moleque
Author-email: molecada@yandex.ru
Requires-Python: >=3.6,<4.0
Classifier: License :: Other/Proprietary License
Classifier: Programming Language :: Python :: 3
Classifier: Programming Language :: Python :: 3.6
Classifier: Programming Language :: Python :: 3.7
Classifier: Programming Language :: Python :: 3.8
Classifier: Programming Language :: Python :: 3.9
Requires-Dist: boto3 (>=1.17.66,<2.0.0)
